MANIFEST.in
README.rst
setup.py
Ldtools.egg-info/PKG-INFO
Ldtools.egg-info/SOURCES.txt
Ldtools.egg-info/dependency_links.txt
Ldtools.egg-info/entry_points.txt
Ldtools.egg-info/requires.txt
Ldtools.egg-info/top_level.txt
ldtools/__init__.py
ldtools/backends.py
ldtools/cli.py
ldtools/helpers.py
ldtools/metamodels.py
ldtools/models.py
ldtools/origin.py
ldtools/resource.py
ldtools/tools.py
ldtools/utils.py