Metadata-Version: 1.1
Name: Ldtools
Version: 0.8.1
Summary: A lightweight ORM for Linked Data: Consume Linked Data resources, modify the graph and write the changes back to their original source
Home-page: http://github.com/dmr/ldtools
Author: Daniel Rech
Author-email: dr@netsyno.com
License: BSD
Platform: UNKNOWN
Classifier: Development Status :: 4 - Beta
Classifier: Environment :: Web Environment
Classifier: Intended Audience :: Developers
Classifier: Operating System :: OS Independent
Classifier: Programming Language :: Python
Classifier: Programming Language :: Python :: 2.6
Classifier: Programming Language :: Python :: 2.7
Classifier: Programming Language :: Python :: 3.3
Classifier: Programming Language :: Python :: 3.4
Classifier: Programming Language :: Python :: 3.5
Classifier: License :: OSI Approved :: BSD License
